[
  {
      "id": 1,
      "texto": "Desarrollador Visual Basic - Jefe de Desarrollo - Jefe de Tecnología - Responsable del Area de Sistemas de información de la Dirección Nacional de Medicamentos y Tecnología Sanitaria.",
      "desde": "2002",
      "hasta": "2023",
      "id_provincia": "B",
      "id_pais": "AR",
      "provincia": "CABA",
      "pais": "Argentina",
      "n_orden": 1,
      "institucion": [
          {
              "id": 5,
              "institucion": "Ministerio de Salud de la Nación.",
              "link_icono": "https://i.postimg.cc/4dW8t3mh/MSAL-modified.png",
              "titulo": [
                  {
                      "id": 999,
                      "titulo": "Sin titulo"
                  }
              ]
          }
      ]
  }
]